<?xml version="1.0" encoding="UTF-8"?>
<objects serializationModel="Studio.02.03.00">
	<object class="AudioFile" id="{d6d146ff-16f9-4e29-a146-133705a0b516}">
		<property name="assetPath">
			<value>os_player jump_down_stairs_ (3).flac</value>
		</property>
		<property name="frequencyInKHz">
			<value>48</value>
		</property>
		<property name="channelCount">
			<value>2</value>
		</property>
		<property name="length">
			<value>0.15747916666666667</value>
		</property>
		<relationship name="masterAssetFolder">
			<destination>{2615113a-71e0-4e13-977d-786e38be8d0e}</destination>
		</relationship>
	</object>
</objects>
